sinapsis_chat_history/__init__.py
sinapsis_chat_history/helpers/__init__.py
sinapsis_chat_history/helpers/base_provider.py
sinapsis_chat_history/helpers/database_env_var_keys.py
sinapsis_chat_history/helpers/factory.py
sinapsis_chat_history/helpers/postgres_provider.py
sinapsis_chat_history/templates/__init__.py
sinapsis_chat_history/templates/chat_history_base.py
sinapsis_chat_history/templates/chat_history_fetcher.py
sinapsis_chat_history/templates/chat_history_remover.py
sinapsis_chat_history/templates/chat_history_reset.py
sinapsis_chat_history/templates/chat_history_saver.py
sinapsis_chat_history-0.1.5.dist-info/licenses/LICENSE
sinapsis_chat_history-0.1.5.dist-info/METADATA
sinapsis_chat_history-0.1.5.dist-info/WHEEL
sinapsis_chat_history-0.1.5.dist-info/top_level.txt
sinapsis_chat_history-0.1.5.dist-info/RECORD
