Metadata-Version: 2.4
Name: sinapsis-chat-history
Version: 0.1.5
Summary: Package to manage chat history using PostgreSQL.
Author-email: SinapsisAI <dev@sinapsis.tech>
Project-URL: Homepage, https://sinapsis.tech
Project-URL: Documentation, https://docs.sinapsis.tech/docs
Project-URL: Tutorials, https://docs.sinapsis.tech/tutorials
Project-URL: Repository, https://github.com/Sinapsis-AI/sinapsis-chatbots.git
Requires-Python: >=3.10
License-File: LICENSE
Requires-Dist: sinapsis>=0.2.13
Provides-Extra: psycopg
Requires-Dist: psycopg[binary,pool]>=3.2.9; extra == "psycopg"
Provides-Extra: all
Requires-Dist: sinapsis-chat-history[psycopg]; extra == "all"
Dynamic: license-file
